setup.py
dsndxy23_probability/Binomialdistribution.py
dsndxy23_probability/Gaussiandistribution.py
dsndxy23_probability/Generaldistribution.py
dsndxy23_probability/__init__.py
dsndxy23_probability.egg-info/PKG-INFO
dsndxy23_probability.egg-info/SOURCES.txt
dsndxy23_probability.egg-info/dependency_links.txt
dsndxy23_probability.egg-info/not-zip-safe
dsndxy23_probability.egg-info/top_level.txt