Metadata-Version: 1.0
Name: dsndxy23-probability
Version: 0.1
Summary: Gaussian distributions
Home-page: UNKNOWN
Author: UNKNOWN
Author-email: vsrworld1999@gmail.com
License: UNKNOWN
Platform: UNKNOWN
